harbour_orm/__init__.py
harbour_orm/column.py
harbour_orm/enums.py
harbour_orm/orm_executor.py
harbour_orm/orm_model.py
harbour_orm/query_builder.py
harbour_orm/query_builder_helpers.py
harbour_orm/query_functions.py
harbour_orm/query_utils.py
harbour_orm-0.1.36.dist-info/METADATA
harbour_orm-0.1.36.dist-info/WHEEL
harbour_orm-0.1.36.dist-info/top_level.txt
harbour_orm-0.1.36.dist-info/RECORD
