Metadata-Version: 2.2
Name: harbour-orm
Version: 0.1.36
Summary: The best and the first ORM for Google Spanner (Google SQL)
Author-email: Harbour <developers@harbourshare.com>
Project-URL: Homepage, https://github.com/Harbour-Enterprises/Harbour-ORM
Project-URL: Issues, https://github.com/Harbour-Enterprises/Harbour-ORM/issues
Keywords: ORM,Google Spanner,Google SQL
Classifier: Programming Language :: Python :: 3
Requires-Python: >=3.10
Requires-Dist: pydantic<=1.10.17
Requires-Dist: google-cloud-spanner<=3.48.0
Requires-Dist: google-auth<=2.38.0
